setup.cfg
setup.py
Csgo_tm_api.egg-info/PKG-INFO
Csgo_tm_api.egg-info/SOURCES.txt
Csgo_tm_api.egg-info/dependency_links.txt
Csgo_tm_api.egg-info/not-zip-safe
Csgo_tm_api.egg-info/requires.txt
Csgo_tm_api.egg-info/top_level.txt
dist_cstm/__init__.py
dist_cstm/cstm_api.py