Metadata-Version: 2.1
Name: Csgo-tm-api
Version: 0.0
Summary: Allows you to receive information from the https://market.csgo.com/
Author-email: desynq@mail.ru
